papertuner/__init__.py
papertuner/config.py
papertuner/dataset.py
papertuner/train.py
papertuner/utils.py
papertuner-0.2.27.dist-info/METADATA
papertuner-0.2.27.dist-info/WHEEL
papertuner-0.2.27.dist-info/entry_points.txt
papertuner-0.2.27.dist-info/top_level.txt
papertuner-0.2.27.dist-info/RECORD
